{
  "meta": {
    "session_id": "session_1768992296081_3noq2khip",
    "product_type": "b2c",
    "version": "0.1",
    "created_at": "2026-01-21T10:44:58.627Z",
    "last_updated": "2026-01-21T10:46:08.337Z",
    "inputs": {
      "documents": [],
      "urls": [
        {
          "url": "https://www.notion.com/help/category/new-to-notion",
          "fetched_at": "2026-01-21T10:45:56.458Z",
          "title": "Getting started – Notion Help Center"
        }
      ],
      "founder_sessions": []
    }
  },
  "facts": {
    "product_identity": {
      "name": {
        "value": "Notion",
        "sources": [
          {
            "source_type": "url",
            "source_ref": "https://www.notion.com/help/category/new-to-notion",
            "captured_at": "2026-01-21T10:46:08.335Z",
            "evidence": "Curious about what Notion is? We'll show you right here, and in the articles to come."
          }
        ],
        "quality_tag": "strong"
      },
      "one_liner": {
        "value": "Welcome to the connected workspace where better, faster work happens.",
        "sources": [
          {
            "source_type": "url",
            "source_ref": "https://www.notion.com/help/category/new-to-notion",
            "captured_at": "2026-01-21T10:46:08.335Z",
            "evidence": "Welcome to the connected workspace where better, faster work happens."
          }
        ],
        "quality_tag": "strong"
      },
      "website": {
        "value": "https://www.notion.com/help/category/new-to-notion",
        "sources": [
          {
            "source_type": "url",
            "source_ref": "https://www.notion.com/help/category/new-to-notion",
            "captured_at": "2026-01-21T10:46:08.335Z",
            "evidence": "SOURCE: https://www.notion.com/help/category/new-to-notion"
          }
        ],
        "quality_tag": "strong"
      }
    }
  },
  "extensions": {
    "b2b": {},
    "b2c": {}
  },
  "derived_insights": {},
  "gaps": {
    "current": [],
    "history": []
  },
  "conflicts": []
}